LICENSE
LICENSE.txt
README.rst
setup.cfg
setup.py
mynameisjames/__init__.py
mynameisjames/james.py
mynameisjames.egg-info/PKG-INFO
mynameisjames.egg-info/SOURCES.txt
mynameisjames.egg-info/dependency_links.txt
mynameisjames.egg-info/top_level.txt