Metadata-Version: 2.1
Name: mynameisjames
Version: 0.0.2
Summary: who is james?
Home-page: https://github.com/unclexjames/mynameisjames
Download-URL: https://github.com/unclexjames/mynameisjames
Author: james
Author-email: ------@gmail.com
License: MIT
Keywords: James,ASCII ART
Classifier: Development Status :: 3 - Alpha
Classifier: Intended Audience :: Education
Classifier: Topic :: Utilities
Classifier: License :: OSI Approved :: MIT License
Classifier: Programming Language :: Python :: 3
Classifier: Programming Language :: Python :: 3.4
Classifier: Programming Language :: Python :: 3.5
Classifier: Programming Language :: Python :: 3.6
Classifier: Programming Language :: Python :: 3.7
Classifier: Programming Language :: Python :: 3.8
Classifier: Programming Language :: Python :: 3.9
Classifier: Programming Language :: Python :: 3.10
License-File: LICENSE
License-File: LICENSE.txt
